{"organizations": [], "uuid": "2a9ac8e5ff0a41d1fdd82452978dedb1ccf7d1ea", "thread": {"social": {"gplus": {"shares": 0}, "pinterest": {"shares": 0}, "vk": {"shares": 0}, "linkedin": {"shares": 0}, "facebook": {"likes": 556, "shares": 556, "comments": 0}, "stumbledupon": {"shares": 0}}, "site_full": "aplus.com", "main_image": "http://images5.aplus.com/uc-up/9c696171-080a-4e24-9697-49e5e724554f/9c696171-080a-4e24-9697-49e5e724554f.format_jpeg.inline_yes.jpg", "site_section": "http://aplus.com/feed", "section_title": "Breaking News and Latest News From Around The World | A Plus  latest stories", "url": "http://aplus.com/a/carter-blanchard-vitiligo-dog-rowdy-photos?no_monetization=true", "country": "US", "domain_rank": 4080, "title": "This 8-Year-Old With Vitiligo Found Comfort After He Met A Dog With The Same Skin Condition", "performance_score": 5, "site": "aplus.com", "participants_count": 0, "title_full": "This 8-Year-Old With Vitiligo Found Comfort After He Met A Dog With The Same Skin Condition", "spam_score": 0.0, "site_type": "blogs", "published": "2017-03-22T22:57:00.000+02:00", "replies_count": 0, "uuid": "2a9ac8e5ff0a41d1fdd82452978dedb1ccf7d1ea"}, "author": "", "url": "http://aplus.com/a/carter-blanchard-vitiligo-dog-rowdy-photos?no_monetization=true", "ord_in_thread": 0, "title": "This 8-Year-Old With Vitiligo Found Comfort After He Met A Dog With The Same Skin Condition", "locations": [], "entities": {"persons": [{"name": "adcock", "sentiment": "none"}, {"name": "stephanie adcock", "sentiment": "none"}, {"name": "niki umbenhower", "sentiment": "none"}, {"name": "carter blanchard", "sentiment": "none"}, {"name": "katu", "sentiment": "none"}, {"name": "carter", "sentiment": "none"}, {"name": "rowdy", "sentiment": "none"}, {"name": "heather cichowski", "sentiment": "none"}], "locations": [{"name": "oregon", "sentiment": "none"}, {"name": "arkansas", "sentiment": "none"}], "organizations": [{"name": "katu", "sentiment": "none"}]}, "highlightText": "", "language": "english", "persons": [], "text": "This 8-Year-Old With Vitiligo Found Comfort After He Met A Dog With The Same Skin Condition \"It couldn’t be any other person that made him feel better. It had to be Rowdy.\" Heather Cichowski @heatherceditor Mar 22, 2017 \nCarter Blanchard was diagnosed with vitiligo when he was in kindergarten. The long-term skin condition causes patches of skin to lose their melanin and turn white. When the 8-year-old from Arkansas noticed the skin around his eyes starting to lose pigment, he began to lose confidence. \nCarter's mom, Stephanie Adcock, said that her son would get home from school and the first thing he would say was that he hated his face and the way he looked . Then Adcock came across Rowdy, a black labrador retriever with the same skin condition. \nShe found the 13-year-old dog's photo online where he is nicknamed White Eyed Rowdy thanks to his distinct spots around his eyes. Adcock showed the photos to her son before beginning a correspondence with Rowdy's owner, Niki Umbenhower, who is based in Oregon. \nAdcock told KATU that just seeing the photos of Rowdy impacted her son. He was thrilled to see a dog who had the same condition as him and who was famous for helping kids with it. However, things got even better when Carter and his family had the opportunity to meet Rowdy in person after KATU viewers donated money for the trip across the country. \nRowdy's owners shared a sweet photo on Instagram of the pooch and Carter cuddling and wrote in the caption, \"Dreams came true tonight!!! Carter and I were finally able to meet in person!\"", "external_links": [], "published": "2017-03-22T22:57:00.000+02:00", "crawled": "2017-03-23T07:04:17.664+02:00", "highlightTitle": ""}