{"organizations": [], "uuid": "2eefd2dc22fdd0c11256a7c9bb921b014c8f4baf", "thread": {"social": {"gplus": {"shares": 1}, "pinterest": {"shares": 0}, "vk": {"shares": 0}, "linkedin": {"shares": 0}, "facebook": {"likes": 186, "shares": 186, "comments": 0}, "stumbledupon": {"shares": 0}}, "site_full": "brobible.com", "main_image": "", "site_section": "http://brobible.com", "section_title": "BroBible", "url": "http://brobible.com/entertainment/article/jason-aldean-hunting-property-real-estate/", "country": "US", "domain_rank": 4556, "title": "Country Music Mega Star Jason Aldean Is Selling His Badass Tennessee Hunting Property For A Cool $4.6 Million", "performance_score": 1, "site": "brobible.com", "participants_count": 1, "title_full": "Country Music Mega Star Jason Aldean Is Selling His Badass Tennessee Hunting Property For A Cool $4.6 Million", "spam_score": 0.0, "site_type": "blogs", "published": "2017-03-09T05:01:00.000+02:00", "replies_count": 0, "uuid": "2eefd2dc22fdd0c11256a7c9bb921b014c8f4baf"}, "author": "Cass Anderson", "url": "http://brobible.com/entertainment/article/jason-aldean-hunting-property-real-estate/", "ord_in_thread": 0, "title": "Country Music Mega Star Jason Aldean Is Selling His Badass Tennessee Hunting Property For A Cool $4.6 Million", "locations": [], "entities": {"persons": [], "locations": [], "organizations": []}, "highlightText": "", "language": "english", "persons": [], "text": "Via Black Jack Ridge \n\nSince his debut in 2005, Country Music superstar Jason Aldean has had 18 singles reach #1 on the Country Music charts, and another 8 singles hit the top 10. His 2010 album is certified as going quadruple-platinum, 2012 album double-platinum, and Jason’s 2016 album has already gone single platinum. That’s a shit ton of records being sold by Jason Aldean , and that leads to a whole lot of coin landing in Jason’s bank account.\nOne of the major purchases Jason’s made during his ascent to Country Music superstardom is a 1,436-acre hunting property in Centerville, Tennessee. The property, known as Black Jack Ridge, is littered with streams for fishing and big ol’ bucks for hunting . For years, Black Jack Ridge has been a respite for Jason Aldean when he wants to get away from Nashville and the life of a Country Music celebrity, but Jason’s put his hunting property on the market for a cool $4,599,000 .\nThe hunting shack built on Black Jack Ridge is everything you’d ever want when purchasing a sprawling estate built primarily for spending time in the great outdoors :\nVia Black Jack Ridge \n\nVia Black Jack Ridge \n\nVia Black Jack Ridge \n\nVia Black Jack Ridge \n\nVia Black Jack Ridge \n\nVia Black Jack Ridge \n\nVia Black Jack Ridge \n\nThe cabin on Black Jack Ridge features 6 bedrooms, 5.5 bathrooms, and a 3 bay garage. You can see all sorts of photographs and information about this property on the Black Jack Ridge website where it’s listed at $4,599,000.\n(Shout out to OutdoorHub for sharing this news story!) \n", "external_links": [], "published": "2017-03-09T05:01:00.000+02:00", "crawled": "2017-03-09T00:04:36.411+02:00", "highlightTitle": ""}